README.md
license
setup.py
visual_sponge/__init__.py
visual_sponge/__main__.py
visual_sponge/backend.py
visual_sponge/conf.ini
visual_sponge.egg-info/PKG-INFO
visual_sponge.egg-info/SOURCES.txt
visual_sponge.egg-info/dependency_links.txt
visual_sponge.egg-info/entry_points.txt
visual_sponge.egg-info/requires.txt
visual_sponge.egg-info/top_level.txt
visual_sponge/commands/__init__.py
visual_sponge/commands/configure.py
visual_sponge/commands/default.py
visual_sponge/commands/delete.py
visual_sponge/commands/help.py
visual_sponge/commands/hide.py
visual_sponge/commands/model.py
visual_sponge/commands/movie.py
visual_sponge/commands/printscreen.py
visual_sponge/commands/show.py
visual_sponge/commands/traj.py
visual_sponge/commands/version.py
visual_sponge/parsers/__init__.py
visual_sponge/parsers/mol2.py
visual_sponge/parsers/sponge.py
visual_sponge/parsers/xyz.py
visual_sponge/static/3dmol.js
visual_sponge/static/__init__.py
visual_sponge/static/button.css
visual_sponge/static/codemirror.css
visual_sponge/static/codemirror.js
visual_sponge/static/favicon.ico
visual_sponge/static/fileIcon.png
visual_sponge/static/folderIcon.png
visual_sponge/static/myCodeMirror.js
visual_sponge/static/navi.css
visual_sponge/templates/__init__.py
visual_sponge/templates/index.html
visual_sponge/templates/myCodeMirrorCommands.js
visual_sponge/templates/open_file.html
visual_sponge/templates/setting.html
visual_sponge/templates/translation.js
visual_sponge/translation/__init__.py
visual_sponge/translation/chinese.py
visual_sponge/translation/english.py
visual_sponge/utils/__init__.py
visual_sponge/utils/ffmpeg.py