Metadata-Version: 2.1
Name: visual-sponge
Version: 0.6.4
Summary: A python package to do the visualization for molecular simulations
Author: Yijie Xia
Author-email: yijiexia@pku.edu.cn
Classifier: Programming Language :: Python :: 3 :: Only
Classifier: Development Status :: 5 - Production/Stable
Classifier: Operating System :: OS Independent
Requires-Python: >=3.6
Provides-Extra: pyffmpeg
License-File: license
